CHANGES
MANIFEST.in
README
setup.py
jsonpublish/__init__.py
jsonpublish/encoder.py
jsonpublish/tests.py
jsonpublish.egg-info/PKG-INFO
jsonpublish.egg-info/SOURCES.txt
jsonpublish.egg-info/dependency_links.txt
jsonpublish.egg-info/not-zip-safe
jsonpublish.egg-info/requires.txt
jsonpublish.egg-info/top_level.txt