Metadata-Version: 1.0
Name: jsonpublish
Version: 0.1.3
Summary: Publish Python object as JSON documents
Home-page: UNKNOWN
Author: Andrey Popp
Author-email: 8mayday@gmail.com
License: UNKNOWN
Platform: UNKNOWN
